LICENSE
README.md
setup.py
rst2dep/__init__.py
rst2dep/__main__.py
rst2dep/classes.py
rst2dep/dep2rst.py
rst2dep/example.conllu
rst2dep/example.rs3
rst2dep/example.rs4
rst2dep/example.rsd
rst2dep/feature_extraction.py
rst2dep/rst2dep.py
rst2dep/rst2rels.py
rst2dep/run_tests.py
rst2dep.egg-info/PKG-INFO
rst2dep.egg-info/SOURCES.txt
rst2dep.egg-info/dependency_links.txt
rst2dep.egg-info/requires.txt
rst2dep.egg-info/top_level.txt