Metadata-Version: 2.1
Name: rst2dep
Version: 1.4.0.1
Summary: RST (Rhetorical Structure Theory) constituent and dependency converter for discourse parses
Home-page: https://github.com/amir-zeldes/rst2dep
Download-URL: https://github.com/amir-zeldes/rst2dep/releases/tag/v1.4.0.1
Author: Amir Zeldes
Author-email: amir.zeldes@georgetown.edu
License: Apache License, Version 2.0
Keywords: NLP,RST,discourse,dependencies,converter,conversion,Rhetorical Structure Theory,parsing
Classifier: Programming Language :: Python
Classifier: Programming Language :: Python :: 2
Classifier: Programming Language :: Python :: 3
Classifier: License :: OSI Approved :: Apache Software License
Classifier: Operating System :: OS Independent
License-File: LICENSE
